localfinder/__init__.py
localfinder/__main__.py
localfinder/pipeline.py
localfinder/utils.py
localfinder/commands/__init__.py
localfinder/commands/bin.py
localfinder/commands/calc.py
localfinder/commands/findreg.py
localfinder/commands/simbg.py
localfinder/commands/viz.py
localfinder-0.1.28.dist-info/licenses/LICENSE
localfinder-0.1.28.dist-info/METADATA
localfinder-0.1.28.dist-info/WHEEL
localfinder-0.1.28.dist-info/entry_points.txt
localfinder-0.1.28.dist-info/top_level.txt
localfinder-0.1.28.dist-info/RECORD
