Metadata-Version: 2.4
Name: localfinder
Version: 0.1.28
Summary: localfinder – calculate weighted local correlation (hmC) and enrichment significance (ES) between two genomic tracks, optionally discover significantly different regions(SDRs), and visualise results
Author: Pengfei Yin
Author-email: Pengfei Yin <12133074@mail.sustech.edu.cn>
Classifier: Development Status :: 4 - Beta
Classifier: Programming Language :: Python :: 3
Classifier: Intended Audience :: Science/Research
Classifier: Topic :: Scientific/Engineering :: Bio-Informatics
Classifier: License :: OSI Approved :: MIT License
Classifier: Operating System :: OS Independent
Requires-Python: >=3.9
License-File: LICENSE
Requires-Dist: numpy
Requires-Dist: statsmodels
Requires-Dist: pandas
Requires-Dist: scipy
Requires-Dist: matplotlib
Requires-Dist: plotly
Requires-Dist: pyGenomeTracks
Requires-Dist: scikit-learn
Requires-Dist: argcomplete
Dynamic: license-file
